LihongyiJiqiXuexiBijiLeemlNotesFix1/README.md
LihongyiJiqiXuexiBijiLeemlNotesFix1/__init__.py
LihongyiJiqiXuexiBijiLeemlNotesFix1/__main__.py
LihongyiJiqiXuexiBijiLeemlNotesFix1/file.epub
LihongyiJiqiXuexiBijiLeemlNotesFix1/index.html
LihongyiJiqiXuexiBijiLeemlNotesFix1/css/__init__.py
LihongyiJiqiXuexiBijiLeemlNotesFix1/css/annotations.css
LihongyiJiqiXuexiBijiLeemlNotesFix1/css/main.css
LihongyiJiqiXuexiBijiLeemlNotesFix1/css/normalize.css
LihongyiJiqiXuexiBijiLeemlNotesFix1/css/popup.css
LihongyiJiqiXuexiBijiLeemlNotesFix1/font/__init__.py
LihongyiJiqiXuexiBijiLeemlNotesFix1/font/fontello.eot
LihongyiJiqiXuexiBijiLeemlNotesFix1/font/fontello.svg
LihongyiJiqiXuexiBijiLeemlNotesFix1/font/fontello.ttf
LihongyiJiqiXuexiBijiLeemlNotesFix1/font/fontello.woff
LihongyiJiqiXuexiBijiLeemlNotesFix1/img/__init__.py
LihongyiJiqiXuexiBijiLeemlNotesFix1/img/annotator-glyph-sprite.png
LihongyiJiqiXuexiBijiLeemlNotesFix1/img/annotator-icon-sprite.png
LihongyiJiqiXuexiBijiLeemlNotesFix1/img/apple-touch-icon.png
LihongyiJiqiXuexiBijiLeemlNotesFix1/img/cancelfullscreen.png
LihongyiJiqiXuexiBijiLeemlNotesFix1/img/close.png
LihongyiJiqiXuexiBijiLeemlNotesFix1/img/fullscreen.png
LihongyiJiqiXuexiBijiLeemlNotesFix1/img/loader.gif
LihongyiJiqiXuexiBijiLeemlNotesFix1/img/menu-icon.png
LihongyiJiqiXuexiBijiLeemlNotesFix1/img/save.png
LihongyiJiqiXuexiBijiLeemlNotesFix1/img/saved.png
LihongyiJiqiXuexiBijiLeemlNotesFix1/img/settings-s.png
LihongyiJiqiXuexiBijiLeemlNotesFix1/img/settings.png
LihongyiJiqiXuexiBijiLeemlNotesFix1/img/star.png
LihongyiJiqiXuexiBijiLeemlNotesFix1/js/__init__.py
LihongyiJiqiXuexiBijiLeemlNotesFix1/js/epub.js
LihongyiJiqiXuexiBijiLeemlNotesFix1/js/epub.min.js
LihongyiJiqiXuexiBijiLeemlNotesFix1/js/epub.min.map
LihongyiJiqiXuexiBijiLeemlNotesFix1/js/hooks.min.js
LihongyiJiqiXuexiBijiLeemlNotesFix1/js/hooks.min.map
LihongyiJiqiXuexiBijiLeemlNotesFix1/js/reader.js
LihongyiJiqiXuexiBijiLeemlNotesFix1/js/reader.js.map
LihongyiJiqiXuexiBijiLeemlNotesFix1/js/reader.min.js
lihongyi_jiqi_xuexi_biji_leeml_notes_fix1-2025.3.24.0.dist-info/METADATA
lihongyi_jiqi_xuexi_biji_leeml_notes_fix1-2025.3.24.0.dist-info/WHEEL
lihongyi_jiqi_xuexi_biji_leeml_notes_fix1-2025.3.24.0.dist-info/entry_points.txt
lihongyi_jiqi_xuexi_biji_leeml_notes_fix1-2025.3.24.0.dist-info/top_level.txt
lihongyi_jiqi_xuexi_biji_leeml_notes_fix1-2025.3.24.0.dist-info/RECORD
